sielu/__init__.py
sielu-2.0.0.dist-info/LICENCE.txt
sielu-2.0.0.dist-info/METADATA
sielu-2.0.0.dist-info/WHEEL
sielu-2.0.0.dist-info/top_level.txt
sielu-2.0.0.dist-info/RECORD
